[
 {
   "ac": 18,
   "amb": 123.76,
   "enf": 207.24,
   "ap": 298.93
 },
 {
   "ac": 23,
   "amb": 163.73,
   "enf": 273.56,
   "ap": 394.59
 },
 {
   "ac": 28,
   "amb": 186.98,
   "enf": 314.59,
   "ap": 453.78
 },
 {
   "ac": 33,
   "amb": 208.86,
   "enf": 352.34,
   "ap": 508.23
 },
 {
   "ac": 38,
   "amb": 219.93,
   "enf": 369.96,
   "ap": 533.64
 },
 {
   "ac": 43,
   "amb": 247.2,
   "enf": 418.05,
   "ap": 603.01
 },
 {
   "ac": 48,
   "amb": 302.82,
   "enf": 510.02,
   "ap": 735.67
 },
 {
   "ac": 53,
   "amb": 420.92,
   "enf": 703.83,
   "ap": 1015.22
 },
 {
   "ac": 58,
   "amb": 568.24,
   "enf": 950.17,
   "ap": 1370.55
 },
 {
   "ac": 59,
   "amb": 738.71,
   "enf": 1235.22,
   "ap": 1781.72
 }
]